videostreaming/__init__.py
videostreaming/hosting.py
videostreaming/utils.py
videostreaming-0.2.6.dist-info/LICENSE.txt
videostreaming-0.2.6.dist-info/METADATA
videostreaming-0.2.6.dist-info/WHEEL
videostreaming-0.2.6.dist-info/top_level.txt
videostreaming-0.2.6.dist-info/RECORD
