Metadata-Version: 2.1
Name: videostreaming
Version: 0.2.6
Summary: Small package to simplify video streaming using python built-in socket library
Home-page: https://github.com/MikiTwenty/Python/tree/main/Libraries/video-streaming
Author: MikiTwenty
Author-email: terminetor.xx@gmail.com
License: MIT
Keywords: python,socket,streaming,server,client
Classifier: License :: OSI Approved :: MIT License
Classifier: Programming Language :: Python :: 3.10
Classifier: Operating System :: OS Independent
License-File: LICENSE.txt
Requires-Dist: opencv-python
